hannibal/__init__.py
hannibal/parser/__init__.py
hannibal/parser/parser.py
hannibal/spider/__init__.py
hannibal/spider/distribute_collector.py
hannibal/spider/local_collector.py
hannibal/util/__init__.py
hannibal/util/common_utils.py
hannibal/util/href_pool.py
hannibal/util/queues.py
hannibal/util/tricks.py
hannibal-0.0.9.dist-info/METADATA
hannibal-0.0.9.dist-info/RECORD
hannibal-0.0.9.dist-info/WHEEL
hannibal-0.0.9.dist-info/top_level.txt
